// Compiled from Password.java (version 12 : 56.0, super bit)
public class Encrpt.encryption.Password {
  
  // Field descriptor #6 Ljava/lang/String;
  private java.lang.String password;
  
  // Field descriptor #6 Ljava/lang/String;
  private java.lang.String salt;
  
  // Field descriptor #6 Ljava/lang/String;
  private java.lang.String pin;
  
  // Field descriptor #10 [C
  char[] pswd;
  
  // Field descriptor #10 [C
  char[] saltConverting;
  
  // Field descriptor #10 [C
  char[] pinchar;
  
  // Method descriptor #14 ()V
  // Stack: 2, Locals: 1
  public Password();
     0  aload_0 [this]
     1  invokespecial java.lang.Object() [16]
     4  aload_0 [this]
     5  aload_0 [this]
     6  getfield com.encryption.Password.password : java.lang.String [18]
     9  invokevirtual java.lang.String.toCharArray() : char[] [20]
    12  putfield com.encryption.Password.pswd : char[] [26]
    15  aload_0 [this]
    16  aload_0 [this]
    17  getfield com.encryption.Password.salt : java.lang.String [28]
    20  invokevirtual java.lang.String.toCharArray() : char[] [20]
    23  putfield com.encryption.Password.saltConverting : char[] [30]
    26  aload_0 [this]
    27  aload_0 [this]
    28  getfield com.encryption.Password.pin : java.lang.String [32]
    31  invokevirtual java.lang.String.toCharArray() : char[] [20]
    34  putfield com.encryption.Password.pinchar : char[] [34]
    37  return
      Line numbers:
        [pc: 0, line: 9]
        [pc: 4, line: 15]
        [pc: 15, line: 16]
        [pc: 26, line: 17]
        [pc: 37, line: 9]
      Local variable table:
        [pc: 0, pc: 38] local: this index: 0 type: com.encryption.Password
  
  // Method descriptor #14 ()V
  // Stack: 2, Locals: 3
  public void disp();
     0  ldc <String "pawan"> [41]
     2  astore_1 [name]
     3  aload_1 [name]
     4  invokevirtual java.lang.String.toCharArray() : char[] [20]
     7  astore_2 [chr]
     8  getstatic java.lang.System.out : java.io.PrintStream [43]
    11  aload_2 [chr]
    12  invokevirtual java.io.PrintStream.println(char[]) : void [49]
    15  return
      Line numbers:
        [pc: 0, line: 21]
        [pc: 3, line: 22]
        [pc: 8, line: 23]
        [pc: 15, line: 24]
      Local variable table:
        [pc: 0, pc: 16] local: this index: 0 type: com.encryption.Password
        [pc: 3, pc: 16] local: name index: 1 type: java.lang.String
        [pc: 8, pc: 16] local: chr index: 2 type: char[]
  
  // Method descriptor #58 ([Ljava/lang/String;)V
  // Stack: 4, Locals: 6
  public static void main(java.lang.String[] args);
      0  getstatic java.lang.System.out : java.io.PrintStream [43]
      3  ldc <String "\nWelcome to the Encoding Test Class"> [59]
      5  invokevirtual java.io.PrintStream.println(java.lang.String) : void [61]
      8  new java.util.Scanner [64]
     11  dup
     12  getstatic java.lang.System.in : java.io.InputStream [66]
     15  invokespecial java.util.Scanner(java.io.InputStream) [70]
     18  astore_1 [scan]
     19  getstatic java.lang.System.out : java.io.PrintStream [43]
     22  ldc <String "Enter the String you wanted to decode"> [73]
     24  invokevirtual java.io.PrintStream.println(java.lang.String) : void [61]
     27  aload_1 [scan]
     28  invokevirtual java.util.Scanner.nextLine() : java.lang.String [75]
     31  astore_2 [password]
     32  invokestatic java.util.Base64.getEncoder() : java.util.Base64$Encoder [79]
     35  aload_2 [password]
     36  invokevirtual java.lang.String.getBytes() : byte[] [85]
     39  invokevirtual java.util.Base64$Encoder.encodeToString(byte[]) : java.lang.String [89]
     42  astore_3 [encodePassword]
     43  getstatic java.lang.System.out : java.io.PrintStream [43]
     46  new java.lang.StringBuilder [95]
     49  dup
     50  ldc <String "The Encoded Msg :"> [97]
     52  invokespecial java.lang.StringBuilder(java.lang.String) [99]
     55  aload_3 [encodePassword]
     56  invokevirtual java.lang.StringBuilder.append(java.lang.String) : java.lang.StringBuilder [101]
     59  invokevirtual java.lang.StringBuilder.toString() : java.lang.String [105]
     62  invokevirtual java.io.PrintStream.println(java.lang.String) : void [61]
     65  invokestatic java.util.Base64.getDecoder() : java.util.Base64$Decoder [108]
     68  aload_3 [encodePassword]
     69  invokevirtual java.util.Base64$Decoder.decode(java.lang.String) : byte[] [112]
     72  astore 4 [decodePassword]
     74  new java.lang.String [21]
     77  dup
     78  aload 4 [decodePassword]
     80  invokespecial java.lang.String(byte[]) [118]
     83  astore 5 [getDecode]
     85  getstatic java.lang.System.out : java.io.PrintStream [43]
     88  new java.lang.StringBuilder [95]
     91  dup
     92  ldc <String "\nThe Decode Msg : "> [121]
     94  invokespecial java.lang.StringBuilder(java.lang.String) [99]
     97  aload 5 [getDecode]
     99  invokevirtual java.lang.StringBuilder.append(java.lang.String) : java.lang.StringBuilder [101]
    102  invokevirtual java.lang.StringBuilder.toString() : java.lang.String [105]
    105  invokevirtual java.io.PrintStream.println(java.lang.String) : void [61]
    108  return
      Line numbers:
        [pc: 0, line: 41]
        [pc: 8, line: 180]
        [pc: 19, line: 181]
        [pc: 27, line: 182]
        [pc: 32, line: 184]
        [pc: 43, line: 185]
        [pc: 65, line: 187]
        [pc: 74, line: 188]
        [pc: 85, line: 189]
        [pc: 108, line: 195]
      Local variable table:
        [pc: 0, pc: 109] local: args index: 0 type: java.lang.String[]
        [pc: 19, pc: 109] local: scan index: 1 type: java.util.Scanner
        [pc: 32, pc: 109] local: password index: 2 type: java.lang.String
        [pc: 43, pc: 109] local: encodePassword index: 3 type: java.lang.String
        [pc: 74, pc: 109] local: decodePassword index: 4 type: byte[]
        [pc: 85, pc: 109] local: getDecode index: 5 type: java.lang.String

  Inner classes:
    [inner class info: #113 java/util/Base64$Decoder, outer class info: #80 java/util/Base64
     inner name: #134 Decoder, accessflags: 9 public static],
    [inner class info: #90 java/util/Base64$Encoder, outer class info: #80 java/util/Base64
     inner name: #135 Encoder, accessflags: 9 public static]
}